{"schema":6,"addons":[{"id":"mozilla_cc3@internetdownloadmanager.com","icons":{"32":"https://addons.mozilla.org/user-media/addon_icons/797/797233-32.png?modified=5769629f","64":"https://addons.mozilla.org/user-media/addon_icons/797/797233-64.png?modified=5769629f","128":"https://addons.mozilla.org/user-media/addon_icons/797/797233-128.png?modified=5769629f"},"name":"IDM Integration Module","version":"6.41.1","sourceURI":"https://addons.mozilla.org/firefox/downloads/file/3954034/tonec_idm_integration_module-6.41.1.xpi","homepageURL":"http://www.internetdownloadmanager.com/","supportURL":"https://www.internetdownloadmanager.com/","description":"Download files with Internet Download Manager","fullDescription":"Adds \"Download with IDM\" context menu item for links, adds \"Download panel\", and helps to intercept downloads. This add-on works only when \"Internet Download Manager\" application is installed","weeklyDownloads":54661,"type":"extension","creator":{"name":"Internet Download Manager, Tonec Inc.","url":"https://addons.mozilla.org/en-US/firefox/user/111844/"},"developers":[],"screenshots":[{"url":"https://addons.mozilla.org/user-media/previews/full/230/230932.png?modified=1622132716","width":640,"height":400,"thumbnailURL":"https://addons.mozilla.org/user-media/previews/thumbs/230/230932.jpg?modified=1622132716","thumbnailWidth":533,"thumbnailHeight":333}],"contributionURL":"","averageRating":4.5857,"reviewCount":401,"reviewURL":"https://addons.mozilla.org/en-US/firefox/addon/tonec-idm-integration-module/reviews/","updateDate":1653505930000}]}